start.py
morfometria/butta.py
morfometria/image_aligner.py
morfometria/inserisci_landmarks.py
morfometria/landmarks.py
morfometria/layer_manager.py
morfometria/main.py
morfometria/plugin_allinea_spezzata.py
morfometria/plugin_allinea_spezzata_vs2.py
morfometria/plugin_arti.py
morfometria/plugin_calibrazione.py
morfometria/plugin_gestione_layers.py
morfometria/plugin_spezzata_curva.py
morfometria/rileva_contorno.py
morfometria/rileva_landmarks_vs9.py
morfometria/save_data.py
morfometria/settings_landmarks.py
morfometria-0.0.4.dist-info/licenses/LICENSE
morfometria-0.0.4.dist-info/METADATA
morfometria-0.0.4.dist-info/WHEEL
morfometria-0.0.4.dist-info/entry_points.txt
morfometria-0.0.4.dist-info/top_level.txt
morfometria-0.0.4.dist-info/RECORD
