Metadata-Version: 2.4
Name: Morfometria
Version: 0.0.4
Summary: Morfometria
Author-email: Sergio Castellano <sergio.castellano@unito.it>, Olivier Friard <olivier.friard@unito.it>
License-Expression: GPL-3.0-only
Classifier: Operating System :: OS Independent
Classifier: Intended Audience :: Science/Research
Classifier: Intended Audience :: Education
Classifier: Programming Language :: Python :: 3.13
Classifier: Topic :: Scientific/Engineering
Classifier: Topic :: Scientific/Engineering :: Visualization
Classifier: Operating System :: OS Independent
Requires-Python: >=3.12
License-File: LICENSE
Requires-Dist: numpy>=2.2.5
Requires-Dist: opencv-python>=4.11.0.86
Requires-Dist: pyside6>=6.9.0
Dynamic: license-file
